boilergram/__init__.py
boilergram-0.1.0.dist-info/LICENSE
boilergram-0.1.0.dist-info/METADATA
boilergram-0.1.0.dist-info/WHEEL
boilergram-0.1.0.dist-info/RECORD
